MANIFEST.in
README.md
setup.py
breadpool/__init__.py
breadpool/pool.py
breadpool.egg-info/PKG-INFO
breadpool.egg-info/SOURCES.txt
breadpool.egg-info/dependency_links.txt
breadpool.egg-info/not-zip-safe
breadpool.egg-info/top_level.txt
docs/breadpool.rst
docs/breadpool.tests.rst
docs/conf.py
docs/index.rst
docs/make.bat