Metadata-Version: 1.1
Name: breadpool
Version: 0.0.5
Summary: A Python Thread Pool and a Scheduled Executor
Home-page: https://github.com/chamilad/breadpool
Author: Chamila de Alwis
Author-email: cs@chamiladealwis.com
License: Apache v2.0
Keywords: python thread pool scheduled executor
Platform: UNKNOWN
Classifier: Development Status :: 4 - Beta
Classifier: Intended Audience :: Developers
Classifier: License :: OSI Approved :: Apache Software License
Classifier: Natural Language :: English
Classifier: Operating System :: Unix
Classifier: Programming Language :: Python :: 2.7
Classifier: Topic :: Software Development :: Libraries
